glomar_gridding/__init__.py
glomar_gridding/climatology.py
glomar_gridding/constants.py
glomar_gridding/covariance_tools.py
glomar_gridding/distances.py
glomar_gridding/error_covariance.py
glomar_gridding/grid.py
glomar_gridding/interpolation_covariance.py
glomar_gridding/io.py
glomar_gridding/kriging.py
glomar_gridding/mask.py
glomar_gridding/stochastic.py
glomar_gridding/types.py
glomar_gridding/utils.py
glomar_gridding/variogram.py
glomar_gridding/ellipse/__init__.py
glomar_gridding/ellipse/covariance.py
glomar_gridding/ellipse/estimate.py
glomar_gridding/ellipse/model.py
glomar_gridding-1.0.1.dist-info/METADATA
glomar_gridding-1.0.1.dist-info/WHEEL
glomar_gridding-1.0.1.dist-info/licenses/LICENSE
glomar_gridding-1.0.1.dist-info/RECORD
