Metadata-Version: 2.4
Name: glomar_gridding
Version: 1.0.1
Summary: National Oceanography Centre library for performing gridding.
Project-URL: Repository, https://git.noc.ac.uk/nocsurfaceprocesses/glomar_gridding.git
Author-email: Joseph Siddons <josidd@noc.ac.uk>, Agnieszka Faulkner <agfaul@noc.ac.uk>, Richard Cornes <rcornes@noc.ac.uk>, Steven Chan <stchan@noc.ac.uk>
Maintainer-email: Joseph Siddons <josidd@noc.ac.uk>, Agnieszka Faulkner <agfaul@noc.ac.uk>, Steven Chan <stchan@noc.ac.uk>
License-File: LICENSE
Keywords: covariance,gridding,interpolation,kriging,observations,ordinary,simple
Classifier: Development Status :: 5 - Production/Stable
Classifier: Intended Audience :: Science/Research
Classifier: Operating System :: OS Independent
Classifier: Programming Language :: Python :: 3.11
Classifier: Programming Language :: Python :: 3.12
Classifier: Programming Language :: Python :: 3.13
Requires-Python: >=3.11
Requires-Dist: geopandas
Requires-Dist: netcdf4
Requires-Dist: numpy!=2.2.6
Requires-Dist: pandas
Requires-Dist: polars
Requires-Dist: pyarrow
Requires-Dist: pyyaml>=6.0.2
Requires-Dist: scikit-learn
Requires-Dist: scipy
Requires-Dist: statsmodels>=0.14.4
Requires-Dist: tqdm
Requires-Dist: xarray
Provides-Extra: all
Requires-Dist: cartopy; extra == 'all'
Requires-Dist: ipykernel; extra == 'all'
Requires-Dist: matplotlib; extra == 'all'
Requires-Dist: sphinx-autodoc-typehints>=3.1.0; extra == 'all'
Requires-Dist: sphinx-rtd-theme>=3.0.2; extra == 'all'
Requires-Dist: sphinx>=8.2.0; extra == 'all'
Provides-Extra: docs
Requires-Dist: sphinx-autodoc-typehints>=3.1.0; extra == 'docs'
Requires-Dist: sphinx-rtd-theme>=3.0.2; extra == 'docs'
Requires-Dist: sphinx>=8.2.0; extra == 'docs'
Provides-Extra: extra
Requires-Dist: ipykernel; extra == 'extra'
Provides-Extra: notebooks
Requires-Dist: cartopy; extra == 'notebooks'
Requires-Dist: matplotlib; extra == 'notebooks'
Provides-Extra: test
Requires-Dist: pytest-cov>=6.1.1; extra == 'test'
Requires-Dist: pytest>=8.3.4; extra == 'test'
